{
  "users": [
    {
      "id": "1",
      "name": "John Doe",
      "email": "john.doe@example.com",
      "password": "123456",
      "projects": [
        {
          "id": "1",
          "name": "Project 1",
          "description": "Project 1 description",
          "content": [
            {
              "id": "f7c22953-5b22-4668-8da2-de2ff944ec7c",
              "type": "paragraph",
              "props": {
                "textColor": "default",
                "backgroundColor": "default",
                "textAlignment": "left"
              },
              "content": [
                {
                  "type": "text",
                  "text": "o gente",
                  "styles": {}
                }
              ],
              "children": []
            },
            {
              "id": "7afba98a-b0cd-45ab-88b2-513a18916f83",
              "type": "numberedListItem",
              "props": {
                "textColor": "default",
                "backgroundColor": "default",
                "textAlignment": "left"
              },
              "content": [
                {
                  "type": "text",
                  "text": "wedfwe",
                  "styles": {}
                }
              ],
              "children": []
            },
            {
              "id": "f32242d9-b8ab-43b1-8b5a-da36ade78ebc",
              "type": "numberedListItem",
              "props": {
                "textColor": "default",
                "backgroundColor": "default",
                "textAlignment": "left"
              },
              "content": [
                {
                  "type": "text",
                  "text": "wefwef",
                  "styles": {}
                }
              ],
              "children": []
            },
            {
              "id": "5c415180-6633-4096-b6ac-04dc72a17c82",
              "type": "numberedListItem",
              "props": {
                "textColor": "default",
                "backgroundColor": "default",
                "textAlignment": "left"
              },
              "content": [
                {
                  "type": "text",
                  "text": "wef",
                  "styles": {}
                }
              ],
              "children": []
            },
            {
              "id": "c722c8f8-00cd-4188-9fe8-0a1ae625355a",
              "type": "paragraph",
              "props": {
                "textColor": "default",
                "backgroundColor": "default",
                "textAlignment": "left"
              },
              "content": [],
              "children": []
            }
          ],
          "updatedAt": "2025-01-31T23:08:08.941Z"
        }
      ]
    }
  ],
  "posts": [],
  "comments": [],
  "institutions": [],
  "forums": [],
  "books": []
}